think_ai/__init__.py
think_ai/__main__.py
think_ai/cli.py
think_ai/benchmarks/__init__.py
think_ai/benchmarks/performance.py
think_ai/cache/__init__.py
think_ai/cache/architecture_cache.py
think_ai/cli/__init__.py
think_ai/cli/main.py
think_ai/coding/__init__.py
think_ai/coding/autonomous_coder.py
think_ai/coding/autonomous_project_builder.py
think_ai/coding/code_executor.py
think_ai/coding/code_generator.py
think_ai/coding/parallel_autonomous_coder.py
think_ai/config/cost_optimization.py
think_ai/consciousness/__init__.py
think_ai/consciousness/awareness.py
think_ai/consciousness/infinite_mind.py
think_ai/consciousness/principles.py
think_ai/consciousness/thought_optimizer.py
think_ai/core/__init__.py
think_ai/core/config.py
think_ai/core/engine.py
think_ai/core/think_ai_eternal.py
think_ai/engine/full_system.py
think_ai/federated/__init__.py
think_ai/federated/federated_learning.py
think_ai/graph/__init__.py
think_ai/graph/knowledge_graph.py
think_ai/integrations/__init__.py
think_ai/integrations/claude_api.py
think_ai/integrations/claude_interface.py
think_ai/intelligence/self_trainer.py
think_ai/internet/browser.py
think_ai/models/__init__.py
think_ai/models/embeddings.py
think_ai/models/fast_language_model.py
think_ai/models/language_model.py
think_ai/models/parallel_model_pool.py
think_ai/models/response_cache.py
think_ai/multimodal/__init__.py
think_ai/multimodal/image_processor.py
think_ai/multimodal/processor.py
think_ai/music/__init__.py
think_ai/music/music_player.py
think_ai/persistence/eternal_memory.py
think_ai/persistence/shared_knowledge.py
think_ai/plugins/__init__.py
think_ai/plugins/base.py
think_ai/plugins/installer.py
think_ai/plugins/manager.py
think_ai/plugins/registry.py
think_ai/plugins/testing.py
think_ai/plugins/examples/ui_visualization.py
think_ai/social/comedian.py
think_ai/social/medium_writer.py
think_ai/social/social_manager.py
think_ai/social/x_twitter_bot.py
think_ai/storage/__init__.py
think_ai/storage/base.py
think_ai-2.0.0.dist-info/METADATA
think_ai-2.0.0.dist-info/WHEEL
think_ai-2.0.0.dist-info/entry_points.txt
think_ai-2.0.0.dist-info/top_level.txt
think_ai-2.0.0.dist-info/RECORD
