Metadata-Version: 2.4
Name: think-ai
Version: 2.0.0
Summary: A self-improving AI system with distributed consciousness that grows smarter with every conversation
Home-page: https://github.com/champi-dev/think_ai
Author: Champi (BDFL)
Author-email: Think AI Team <hello@thinkai.co>
Maintainer-email: Think AI Team <hello@thinkai.co>
License: MIT
Project-URL: Homepage, https://github.com/champi-dev/think_ai
Project-URL: Documentation, https://github.com/champi-dev/think_ai/blob/main/README.md
Project-URL: Repository, https://github.com/champi-dev/think_ai
Project-URL: Issues, https://github.com/champi-dev/think_ai/issues
Project-URL: Changelog, https://github.com/champi-dev/think_ai/blob/main/CHANGELOG.md
Keywords: ai,consciousness,distributed-intelligence,colombia,artificial-intelligence,claude,ollama
Classifier: Development Status :: 4 - Beta
Classifier: Intended Audience :: Developers
Classifier: Topic :: Scientific/Engineering :: Artificial Intelligence
Classifier: License :: OSI Approved :: MIT License
Classifier: Programming Language :: Python :: 3
Classifier: Programming Language :: Python :: 3.8
Classifier: Programming Language :: Python :: 3.9
Classifier: Programming Language :: Python :: 3.10
Classifier: Programming Language :: Python :: 3.11
Classifier: Programming Language :: Python :: 3.12
Classifier: Operating System :: OS Independent
Requires-Python: >=3.8
Requires-Dist: asyncio-throttle==1.0.2
Requires-Dist: structlog==24.1.0
Requires-Dist: rich==13.7.1
Requires-Dist: python-dotenv==1.0.1
Requires-Dist: pyyaml==6.0.1
Requires-Dist: click==8.1.7
Requires-Dist: prompt-toolkit==3.0.43
Requires-Dist: cassandra-driver==3.29.0
Requires-Dist: redis==5.0.1
Requires-Dist: pymilvus==2.3.5
Requires-Dist: neo4j==5.16.0
Requires-Dist: torch>=2.1.0
Requires-Dist: transformers>=4.36.0
Requires-Dist: sentence-transformers==2.2.2
Requires-Dist: numpy==1.24.3
Requires-Dist: scikit-learn==1.3.2
Requires-Dist: fastapi==0.108.0
Requires-Dist: uvicorn==0.25.0
Requires-Dist: aiofiles==23.2.1
Requires-Dist: httpx==0.25.2
Requires-Dist: psutil==5.9.6
Requires-Dist: anthropic>=0.20.0
Requires-Dist: aiohttp>=3.8.0
Requires-Dist: motor>=3.1.0
Requires-Dist: pydantic>=2.0.0
Requires-Dist: typer>=0.9.0
Provides-Extra: dev
Requires-Dist: pytest>=7.0; extra == "dev"
Requires-Dist: pytest-asyncio>=0.20; extra == "dev"
Requires-Dist: pytest-cov>=4.0; extra == "dev"
Requires-Dist: black>=23.0; extra == "dev"
Requires-Dist: ruff>=0.1.0; extra == "dev"
Requires-Dist: mypy>=1.0; extra == "dev"
Provides-Extra: full
Requires-Dist: playwright>=1.30; extra == "full"
Requires-Dist: pillow>=10.0; extra == "full"
Requires-Dist: numpy>=1.24; extra == "full"
Requires-Dist: pandas>=2.0; extra == "full"
Requires-Dist: scikit-learn>=1.3; extra == "full"
Requires-Dist: transformers>=4.30; extra == "full"
Provides-Extra: social
Requires-Dist: tweepy>=4.14; extra == "social"
Requires-Dist: python-twitter>=3.5; extra == "social"
Requires-Dist: requests-oauthlib>=1.3; extra == "social"
Dynamic: author
Dynamic: home-page
Dynamic: requires-python
